extract_msg/__init__.py
extract_msg/__main__.py
extract_msg/enums.py
extract_msg/exceptions.py
extract_msg/null_date.py
extract_msg/ole_writer.py
extract_msg/open_msg.py
extract_msg/py.typed
extract_msg/recipient.py
extract_msg/utils.py
extract_msg/_rtf/__init__.py
extract_msg/_rtf/create_doc.py
extract_msg/_rtf/inject_rtf.py
extract_msg/_rtf/token.py
extract_msg/_rtf/tokenize_rtf.py
extract_msg/attachments/__init__.py
extract_msg/attachments/attachment.py
extract_msg/attachments/attachment_base.py
extract_msg/attachments/broken_att.py
extract_msg/attachments/custom_att.py
extract_msg/attachments/emb_msg_att.py
extract_msg/attachments/signed_att.py
extract_msg/attachments/unsupported_att.py
extract_msg/attachments/web_att.py
extract_msg/attachments/custom_att_handler/__init__.py
extract_msg/attachments/custom_att_handler/custom_handler.py
extract_msg/attachments/custom_att_handler/lnk_obj_att.py
extract_msg/attachments/custom_att_handler/outlook_image_dib.py
extract_msg/attachments/custom_att_handler/outlook_image_meta.py
extract_msg/constants/__init__.py
extract_msg/constants/ps.py
extract_msg/constants/re.py
extract_msg/constants/st.py
extract_msg/data/logging-config/logging-nt.json
extract_msg/data/logging-config/logging-posix.json
extract_msg/encoding/__init__.py
extract_msg/encoding/utils.py
extract_msg/encoding/_dt/__init__.py
extract_msg/encoding/_dt/_mac_ce.py
extract_msg/encoding/_dt/_mac_cyrillic.py
extract_msg/encoding/_dt/_mac_greek.py
extract_msg/encoding/_dt/_mac_iceland.py
extract_msg/encoding/_dt/_mac_turkish.py
extract_msg/encoding/_dt/_win874_dec.py
extract_msg/encoding/_dt/_win950_dec.py
extract_msg/msg_classes/__init__.py
extract_msg/msg_classes/appointment.py
extract_msg/msg_classes/calendar.py
extract_msg/msg_classes/calendar_base.py
extract_msg/msg_classes/contact.py
extract_msg/msg_classes/journal.py
extract_msg/msg_classes/meeting_cancellation.py
extract_msg/msg_classes/meeting_exception.py
extract_msg/msg_classes/meeting_forward.py
extract_msg-0.55.0.dist-info/LICENSE.txt
extract_msg-0.55.0.dist-info/METADATA
extract_msg-0.55.0.dist-info/WHEEL
extract_msg-0.55.0.dist-info/entry_points.txt
extract_msg-0.55.0.dist-info/top_level.txt
extract_msg-0.55.0.dist-info/RECORD
