Metadata-Version: 2.1
Name: extract-msg
Version: 0.55.0
Summary: Extracts emails and attachments saved in Microsoft Outlook's .msg files
Home-page: https://github.com/TeamMsgExtractor/msg-extractor
Download-URL: https://github.com/TeamMsgExtractor/msg-extractor/archives/master
Author: Destiny Peterson & Matthew Walker
Author-email: arceusthe@gmail.com, mattgwwalker@gmail.com
License: GPL
Requires-Python: >=3.8
Provides-Extra: all
Provides-Extra: mime
Provides-Extra: image
Provides-Extra: encoding
Provides-Extra: readthedocs
License-File: LICENSE.txt
